rio_cogeo/__init__.py
rio_cogeo/cogeo.py
rio_cogeo/errors.py
rio_cogeo/models.py
rio_cogeo/profiles.py
rio_cogeo/py.typed
rio_cogeo/utils.py
rio_cogeo/scripts/__init__.py
rio_cogeo/scripts/cli.py
rio_cogeo-7.0.1.dist-info/METADATA
rio_cogeo-7.0.1.dist-info/WHEEL
rio_cogeo-7.0.1.dist-info/entry_points.txt
rio_cogeo-7.0.1.dist-info/licenses/LICENSE
rio_cogeo-7.0.1.dist-info/RECORD
