Metadata-Version: 2.4
Name: rio-cogeo
Version: 7.0.1
Summary: Cloud Optimized GeoTIFF (COGEO) creation plugin for rasterio
Project-URL: Source, https://github.com/cogeotiff/rio-cogeo
Project-URL: Documentation, https://cogeotiff.github.io/rio-cogeo/
Author-email: Vincent Sarago <vincent@developmentseed.com>
License: BSD 3-Clause License
License-File: LICENSE
Keywords: COGEO,CloudOptimized Geotiff,rasterio
Classifier: Intended Audience :: Information Technology
Classifier: Intended Audience :: Science/Research
Classifier: License :: OSI Approved :: BSD License
Classifier: Programming Language :: Python :: 3.11
Classifier: Programming Language :: Python :: 3.12
Classifier: Programming Language :: Python :: 3.13
Classifier: Programming Language :: Python :: 3.14
Classifier: Topic :: Scientific/Engineering :: GIS
Requires-Python: >=3.11
Requires-Dist: click>=7.0
Requires-Dist: morecantile<8.0,>=5.0
Requires-Dist: pydantic~=2.0
Requires-Dist: rasterio>=1.3.3
